coapdialects/__init__.py
coapdialects/blockwise.py
coapdialects/credentials.py
coapdialects/defaults.py
coapdialects/error.py
coapdialects/interfaces.py
coapdialects/message.py
coapdialects/messagemanager.py
coapdialects/meta.py
coapdialects/options.py
coapdialects/optiontypes.py
coapdialects/oscore.py
coapdialects/oscore_sitewrapper.py
coapdialects/pipe.py
coapdialects/protocol.py
coapdialects/resource.py
coapdialects/tokenmanager.py
coapdialects/cli/__init__.py
coapdialects/cli/client.py
coapdialects/cli/common.py
coapdialects/cli/defaults.py
coapdialects/cli/fileserver.py
coapdialects/cli/proxy.py
coapdialects/cli/rd.py
coapdialects/numbers/__init__.py
coapdialects/numbers/codes.py
coapdialects/numbers/constants.py
coapdialects/numbers/contentformat.py
coapdialects/numbers/optionnumbers.py
coapdialects/numbers/types.py
coapdialects/proxy/__init__.py
coapdialects/proxy/client.py
coapdialects/proxy/server.py
coapdialects/resourcedirectory/__init__.py
coapdialects/resourcedirectory/client/__init__.py
coapdialects/resourcedirectory/client/register.py
coapdialects/transports/__init__.py
coapdialects/transports/generic_udp.py
coapdialects/transports/oscore.py
coapdialects/transports/rfc8323common.py
coapdialects/transports/simple6.py
coapdialects/transports/simplesocketserver.py
coapdialects/transports/tcp.py
coapdialects/transports/tinydtls.py
coapdialects/transports/tinydtls_server.py
coapdialects/transports/tls.py
coapdialects/transports/udp6.py
coapdialects/transports/ws.py
coapdialects/util/__init__.py
coapdialects/util/cli.py
coapdialects/util/contenttype.py
coapdialects/util/cryptography_additions.py
coapdialects/util/linkformat.py
coapdialects/util/linkformat_pygments.py
coapdialects/util/prettyprint.py
coapdialects/util/pyodide_websockets.py
coapdialects/util/socknumbers.py
coapdialects/util/uri.py
coapdialects/util/asyncio/__init__.py
coapdialects/util/asyncio/getaddrinfo_addrconfig.py
coapdialects/util/asyncio/recvmsg.py
coapdialects-0.0.9.dist-info/LICENSE
coapdialects-0.0.9.dist-info/METADATA
coapdialects-0.0.9.dist-info/WHEEL
coapdialects-0.0.9.dist-info/top_level.txt
coapdialects-0.0.9.dist-info/RECORD
